cookie_pbs_test/__init__.py
cookie_pbs_test/main.py
cookie_pbs_test-0.0.3.dist-info/LICENSE
cookie_pbs_test-0.0.3.dist-info/METADATA
cookie_pbs_test-0.0.3.dist-info/WHEEL
cookie_pbs_test-0.0.3.dist-info/RECORD
