Metadata-Version: 2.1
Name: cookie-pbs-test
Version: 0.0.3
Summary: testing my cookiecutter 
Home-page: https://github.com/bsalanie/cookie-pbs-test
Author: Bernard Salanie
Author-email: fbsalanie@columbia.edu
Requires-Python: >=3.11,<4.0
Classifier: Programming Language :: Python :: 3
Classifier: Programming Language :: Python :: 3.11
Project-URL: Documentation, https://bsalanie.github.io/cookie-pbs-test/
Project-URL: Repository, https://github.com/bsalanie/cookie-pbs-test
